raducord/__init__.py
raducord-1.0.4.dist-info/LICENSE
raducord-1.0.4.dist-info/METADATA
raducord-1.0.4.dist-info/WHEEL
raducord-1.0.4.dist-info/top_level.txt
raducord-1.0.4.dist-info/RECORD
